tensorflow_tts/__init__.py
tensorflow_tts/bin/__init__.py
tensorflow_tts/bin/preprocess.py
tensorflow_tts/configs/__init__.py
tensorflow_tts/configs/base_config.py
tensorflow_tts/configs/fastspeech.py
tensorflow_tts/configs/fastspeech2.py
tensorflow_tts/configs/hifigan.py
tensorflow_tts/configs/mb_melgan.py
tensorflow_tts/configs/melgan.py
tensorflow_tts/configs/parallel_wavegan.py
tensorflow_tts/configs/tacotron2.py
tensorflow_tts/datasets/__init__.py
tensorflow_tts/datasets/abstract_dataset.py
tensorflow_tts/datasets/audio_dataset.py
tensorflow_tts/datasets/mel_dataset.py
tensorflow_tts/inference/__init__.py
tensorflow_tts/inference/auto_config.py
tensorflow_tts/inference/auto_model.py
tensorflow_tts/inference/auto_processor.py
tensorflow_tts/inference/savable_models.py
tensorflow_tts/losses/__init__.py
tensorflow_tts/losses/spectrogram.py
tensorflow_tts/losses/stft.py
tensorflow_tts/models/__init__.py
tensorflow_tts/models/base_model.py
tensorflow_tts/models/fastspeech.py
tensorflow_tts/models/fastspeech2.py
tensorflow_tts/models/hifigan.py
tensorflow_tts/models/mb_melgan.py
tensorflow_tts/models/melgan.py
tensorflow_tts/models/parallel_wavegan.py
tensorflow_tts/models/tacotron2.py
tensorflow_tts/optimizers/__init__.py
tensorflow_tts/optimizers/adamweightdecay.py
tensorflow_tts/optimizers/gradient_accumulate.py
tensorflow_tts/processor/__init__.py
tensorflow_tts/processor/baker.py
tensorflow_tts/processor/base_processor.py
tensorflow_tts/processor/kss.py
tensorflow_tts/processor/libritts.py
tensorflow_tts/processor/ljspeech.py
tensorflow_tts/processor/synpaflex.py
tensorflow_tts/processor/thorsten.py
tensorflow_tts/trainers/__init__.py
tensorflow_tts/trainers/base_trainer.py
tensorflow_tts/utils/__init__.py
tensorflow_tts/utils/cleaners.py
tensorflow_tts/utils/decoder.py
tensorflow_tts/utils/griffin_lim.py
tensorflow_tts/utils/group_conv.py
tensorflow_tts/utils/korean.py
tensorflow_tts/utils/number_norm.py
tensorflow_tts/utils/outliers.py
TensorFlowTTS-1.8.dist-info/LICENSE
TensorFlowTTS-1.8.dist-info/METADATA
TensorFlowTTS-1.8.dist-info/WHEEL
TensorFlowTTS-1.8.dist-info/entry_points.txt
TensorFlowTTS-1.8.dist-info/top_level.txt
TensorFlowTTS-1.8.dist-info/RECORD
