Metadata-Version: 2.1
Name: TensorFlowTTS
Version: 1.8
Summary: TensorFlowTTS: Real-Time State-of-the-art Speech Synthesis for TensorFlow 2
Home-page: https://github.com/tensorspeech/TensorFlowTTS
Author: Minh Nguyen Quan Anh, Alejandro Miguel Velasquez, Dawid Kobus, Eren Gölge, Kuan Chen, Takuya Ebata, Trinh Le Quang, Yunchao He
Author-email: nguyenquananhminh@gmail.com
License: Apache-2.0
Platform: UNKNOWN
Classifier: Programming Language :: Python :: 3.6
Classifier: Programming Language :: Python :: 3.7
Classifier: Programming Language :: Python :: 3.8
Classifier: Intended Audience :: Science/Research
Classifier: Operating System :: POSIX :: Linux
Classifier: License :: OSI Approved :: Apache Software License
Classifier: Topic :: Software Development :: Libraries :: Python Modules
Requires-Dist: tensorflow-gpu (==2.6.0)
Requires-Dist: tensorflow-addons (>=0.10.0)
Requires-Dist: setuptools (>=38.5.1)
Requires-Dist: huggingface-hub (==0.0.8)
Requires-Dist: librosa (>=0.7.0)
Requires-Dist: soundfile (>=0.10.2)
Requires-Dist: matplotlib (>=3.1.0)
Requires-Dist: PyYAML (>=3.12)
Requires-Dist: tqdm (>=4.26.1)
Requires-Dist: h5py (>=2.10.0)
Requires-Dist: unidecode (>=1.1.1)
Requires-Dist: inflect (>=4.1.0)
Requires-Dist: scikit-learn (>=0.22.0)
Requires-Dist: pyworld (>=0.2.10)
Requires-Dist: numba (<=0.48)
Requires-Dist: jamo (>=0.4.1)
Requires-Dist: pypinyin
Requires-Dist: g2pM
Requires-Dist: textgrid
Requires-Dist: click
Requires-Dist: g2p-en
Requires-Dist: dataclasses
Provides-Extra: test
Requires-Dist: pytest (>=3.3.0) ; extra == 'test'
Requires-Dist: hacking (>=1.1.0) ; extra == 'test'
